MANIFEST.in
README.md
setup.py
django_split_json_widget.egg-info/PKG-INFO
django_split_json_widget.egg-info/SOURCES.txt
django_split_json_widget.egg-info/dependency_links.txt
django_split_json_widget.egg-info/requires.txt
django_split_json_widget.egg-info/top_level.txt
django_split_json_widget.egg-info/zip-safe
splitjson/__init__.py
splitjson/widgets.py