Metadata-Version: 1.1
Name: django-split-json-widget
Version: 1.15
Summary: Provides a widget that renders JSON data as separate, editable inputs.
Home-page: https://github.com/abbasovalex/django-SplitJSONWidget-form
Author: Alexander Abbasov, django-split-json-widget
Author-email: abbasovalex@{nospam}gmail.com
License: MIT
Keywords: json django widget
Platform: any
Classifier: Development Status :: 3 - Alpha
Classifier: Framework :: Django
Classifier: Intended Audience :: Developers
Classifier: License :: OSI Approved :: MIT License
Classifier: Operating System :: OS Independent
Classifier: Programming Language :: Python
Classifier: Programming Language :: Python :: 2.6
Classifier: Programming Language :: Python :: 2.7
Classifier: Topic :: Internet :: WWW/HTTP
